sqzy/__init__.py
sqzy/compress.py
sqzy-0.1.0.dist-info/licenses/LICENSE
sqzy-0.1.0.dist-info/METADATA
sqzy-0.1.0.dist-info/WHEEL
sqzy-0.1.0.dist-info/top_level.txt
sqzy-0.1.0.dist-info/RECORD
