Metadata-Version: 2.4
Name: sqzy
Version: 0.1.0
Summary: Compress JSON-like API responses before sending to LLMs.
Author: Sqzy Contributors
License: MIT
Project-URL: Homepage, https://github.com/your-org/sqzy
Project-URL: Issues, https://github.com/your-org/sqzy/issues
Keywords: json,compression,llm,api,responses
Classifier: Development Status :: 3 - Alpha
Classifier: License :: OSI Approved :: MIT License
Classifier: Programming Language :: Python :: 3
Classifier: Programming Language :: Python :: 3 :: Only
Classifier: Typing :: Typed
Requires-Python: >=3.8
License-File: LICENSE
Provides-Extra: test
Requires-Dist: pytest>=7.0; extra == "test"
Requires-Dist: pytest-asyncio>=0.21; extra == "test"
Requires-Dist: pytest-cov>=4.1; extra == "test"
Dynamic: license-file
